hyperpy/__init__.py
hyperpy/core.py
hyperpy/util.py
py_hyperpy-0.0.5.dist-info/LICENSE
py_hyperpy-0.0.5.dist-info/METADATA
py_hyperpy-0.0.5.dist-info/WHEEL
py_hyperpy-0.0.5.dist-info/top_level.txt
py_hyperpy-0.0.5.dist-info/RECORD
