Metadata-Version: 2.1
Name: py-hyperpy
Version: 0.0.5
Summary: HyperPy: An automatic hyperparameter optimization framework
Home-page: https://github.com/sergiomora03/py-hyperpy
Author: Sergio A. Mora Pardo
Author-email: sergiomora823@gmail.com
License: MIT
Platform: UNKNOWN
Classifier: Development Status :: 5 - Production/Stable
Classifier: Intended Audience :: Developers
Classifier: Topic :: Software Development :: Build Tools
Classifier: License :: OSI Approved :: MIT License
Classifier: Programming Language :: Python :: 3
Classifier: Programming Language :: Python :: 3.7
Classifier: Programming Language :: Python :: 3.8
Requires-Python: >=3.7
License-File: LICENSE
